Tonviewer/Scraping.py
Tonviewer/__init__.py
Tonviewer/coin.py
Tonviewer/wallet.py
Tonviewer-8.0.dist-info/LICENSE
Tonviewer-8.0.dist-info/METADATA
Tonviewer-8.0.dist-info/WHEEL
Tonviewer-8.0.dist-info/top_level.txt
Tonviewer-8.0.dist-info/RECORD
