Metadata-Version: 2.1
Name: Tonviewer
Version: 8.0
Summary: TON Crypto Info Scraper is a Python library that allows you to fetch ( real-time balance of wallet , transactions , price ) data without needing any APIs.
Author: deep
Author-email: asyncpy@proton.me
License: MIT
Classifier: Programming Language :: Python :: 3
Classifier: License :: OSI Approved :: MIT License
Classifier: Operating System :: OS Independent
Requires-Python: >=3.6
License-File: LICENSE
